{"records":[{"id":"hk-2026-06-28-069","source":"hk","sourceName":"香港","year":2025,"issue":69,"date":"2026-06-28","file":"hk1.html","balls":[{"index":0,"number":5,"numberText":"05","color":"green","colorName":"绿","zodiac":"马"},{"index":1,"number":7,"numberText":"07","color":"red","colorName":"红","zodiac":"猪"},{"index":2,"number":26,"numberText":"26","color":"blue","colorName":"蓝","zodiac":"鼠"},{"index":3,"number":32,"numberText":"32","color":"green","colorName":"绿","zodiac":"蛇"},{"index":4,"number":35,"numberText":"35","color":"red","colorName":"红","zodiac":"虎"},{"index":5,"number":37,"numberText":"37","color":"blue","colorName":"蓝","zodiac":"兔"},{"index":6,"number":40,"numberText":"40","color":"red","colorName":"红","zodiac":"猴"}]},{"id":"hk-2026-06-25-068","source":"hk","sourceName":"香港","year":2025,"issue":68,"date":"2026-06-25","file":"hk1.html","balls":[{"index":0,"number":12,"numberText":"12","color":"red","colorName":"红","zodiac":"兔"},{"index":1,"number":16,"numberText":"16","color":"green","colorName":"绿","zodiac":"羊"},{"index":2,"number":19,"numberText":"19","color":"red","colorName":"红","zodiac":"猪"},{"index":3,"number":20,"numberText":"20","color":"blue","colorName":"蓝","zodiac":"牛"},{"index":4,"number":28,"numberText":"28","color":"green","colorName":"绿","zodiac":"兔"},{"index":5,"number":29,"numberText":"29","color":"red","colorName":"红","zodiac":"鼠"},{"index":6,"number":30,"numberText":"30","color":"red","colorName":"红","zodiac":"虎"}]},{"id":"hk-2026-06-23-067","source":"hk","sourceName":"香港","year":2025,"issue":67,"date":"2026-06-23","file":"hk1.html","balls":[{"index":0,"number":2,"numberText":"02","color":"red","colorName":"红","zodiac":"龙"},{"index":1,"number":10,"numberText":"10","color":"blue","colorName":"蓝","zodiac":"虎"},{"index":2,"number":15,"numberText":"15","color":"blue","colorName":"蓝","zodiac":"龙"},{"index":3,"number":25,"numberText":"25","color":"blue","colorName":"蓝","zodiac":"鸡"},{"index":4,"number":34,"numberText":"34","color":"red","colorName":"红","zodiac":"马"},{"index":5,"number":39,"numberText":"39","color":"green","colorName":"绿","zodiac":"蛇"},{"index":6,"number":41,"numberText":"41","color":"blue","colorName":"蓝","zodiac":"鸡"}]},{"id":"hk-2026-06-20-066","source":"hk","sourceName":"香港","year":2025,"issue":66,"date":"2026-06-20","file":"hk1.html","balls":[{"index":0,"number":5,"numberText":"05","color":"green","colorName":"绿","zodiac":"兔"},{"index":1,"number":7,"numberText":"07","color":"red","colorName":"红","zodiac":"鸡"},{"index":2,"number":10,"numberText":"10","color":"blue","colorName":"蓝","zodiac":"鼠"},{"index":3,"number":15,"numberText":"15","color":"blue","colorName":"蓝","zodiac":"虎"},{"index":4,"number":16,"numberText":"16","color":"green","colorName":"绿","zodiac":"龙"},{"index":5,"number":41,"numberText":"41","color":"blue","colorName":"蓝","zodiac":"虎"},{"index":6,"number":46,"numberText":"46","color":"red","colorName":"红","zodiac":"鸡"}]},{"id":"hk-2026-06-18-065","source":"hk","sourceName":"香港","year":2025,"issue":65,"date":"2026-06-18","file":"hk1.html","balls":[{"index":0,"number":6,"numberText":"06","color":"green","colorName":"绿","zodiac":"蛇"},{"index":1,"number":20,"numberText":"20","color":"blue","colorName":"蓝","zodiac":"猪"},{"index":2,"number":24,"numberText":"24","color":"red","colorName":"红","zodiac":"猴"},{"index":3,"number":26,"numberText":"26","color":"blue","colorName":"蓝","zodiac":"鼠"},{"index":4,"number":31,"numberText":"31","color":"blue","colorName":"蓝","zodiac":"鸡"},{"index":5,"number":34,"numberText":"34","color":"red","colorName":"红","zodiac":"牛"},{"index":6,"number":47,"numberText":"47","color":"blue","colorName":"蓝","zodiac":"羊"}]}]}