{"files":[{"name":"2020.html","length":428952,"mtimeUtc":"2026-06-19T16:38:59.8399619Z","cacheFile":"2020.html.json"},{"name":"20201.html","length":35189,"mtimeUtc":"2026-06-19T16:38:55.4864040Z","cacheFile":"20201.html.json"},{"name":"2021.html","length":689574,"mtimeUtc":"2026-06-19T16:38:59.4311231Z","cacheFile":"2021.html.json"},{"name":"20211.html","length":237092,"mtimeUtc":"2026-06-19T16:38:55.1043522Z","cacheFile":"20211.html.json"},{"name":"2022.html","length":687301,"mtimeUtc":"2026-06-19T16:38:59.0370221Z","cacheFile":"2022.html.json"},{"name":"20221.html","length":214720,"mtimeUtc":"2026-06-19T16:38:54.7172878Z","cacheFile":"20221.html.json"},{"name":"2023.html","length":687146,"mtimeUtc":"2026-06-19T16:38:58.6267758Z","cacheFile":"2023.html.json"},{"name":"20231.html","length":279817,"mtimeUtc":"2026-06-19T16:38:54.3298110Z","cacheFile":"20231.html.json"},{"name":"2024.html","length":514880,"mtimeUtc":"2026-06-19T16:38:58.2313482Z","cacheFile":"2024.html.json"},{"name":"20241.html","length":220391,"mtimeUtc":"2026-06-19T16:38:53.9430701Z","cacheFile":"20241.html.json"},{"name":"2025.html","length":549536,"mtimeUtc":"2026-06-19T16:38:57.8252564Z","cacheFile":"2025.html.json"},{"name":"20251.html","length":208662,"mtimeUtc":"2026-06-19T16:38:53.5555996Z","cacheFile":"20251.html.json"},{"name":"am.html","length":260786,"mtimeUtc":"2026-06-19T16:38:51.6284475Z","cacheFile":"am.html.json"},{"name":"am1.html","length":15336,"mtimeUtc":"2026-06-19T16:39:00.2255634Z","cacheFile":"am1.html.json"},{"name":"am100.html","length":156557,"mtimeUtc":"2026-06-19T16:38:57.0284750Z","cacheFile":"am100.html.json"},{"name":"am2.html","length":15337,"mtimeUtc":"2026-06-19T16:38:55.8712633Z","cacheFile":"am2.html.json"},{"name":"am20.html","length":38100,"mtimeUtc":"2026-06-19T16:38:56.2555083Z","cacheFile":"am20.html.json"},{"name":"am200.html","length":260214,"mtimeUtc":"2026-06-19T16:38:57.4164249Z","cacheFile":"am200.html.json"},{"name":"am50.html","length":82517,"mtimeUtc":"2026-06-19T16:38:56.6392798Z","cacheFile":"am50.html.json"},{"name":"hk.html","length":106478,"mtimeUtc":"2026-06-19T16:38:50.4784888Z","cacheFile":"hk.html.json"},{"name":"hk1.html","length":15123,"mtimeUtc":"2026-06-19T16:38:50.8611696Z","cacheFile":"hk1.html.json"},{"name":"hk100.html","length":104830,"mtimeUtc":"2026-06-19T16:38:52.7837656Z","cacheFile":"hk100.html.json"},{"name":"hk2.html","length":15122,"mtimeUtc":"2026-06-19T16:38:51.2418940Z","cacheFile":"hk2.html.json"},{"name":"hk20.html","length":38198,"mtimeUtc":"2026-06-19T16:38:52.0118673Z","cacheFile":"hk20.html.json"},{"name":"hk200.html","length":104830,"mtimeUtc":"2026-06-19T16:38:53.1688694Z","cacheFile":"hk200.html.json"},{"name":"hk50.html","length":82617,"mtimeUtc":"2026-06-19T16:38:52.3939213Z","cacheFile":"hk50.html.json"}]}