{"files":[{"name":"2020.html","length":428952,"mtimeUtc":"2026-06-05T16:19:25.6020343Z","cacheFile":"2020.html.json"},{"name":"20201.html","length":35189,"mtimeUtc":"2026-06-05T16:19:20.0609084Z","cacheFile":"20201.html.json"},{"name":"2021.html","length":689574,"mtimeUtc":"2026-06-05T16:19:25.0976938Z","cacheFile":"2021.html.json"},{"name":"20211.html","length":237092,"mtimeUtc":"2026-06-05T16:19:19.5674699Z","cacheFile":"20211.html.json"},{"name":"2022.html","length":687301,"mtimeUtc":"2026-06-05T16:19:24.5940953Z","cacheFile":"2022.html.json"},{"name":"20221.html","length":214720,"mtimeUtc":"2026-06-05T16:19:19.0729321Z","cacheFile":"20221.html.json"},{"name":"2023.html","length":687146,"mtimeUtc":"2026-06-05T16:19:24.0718397Z","cacheFile":"2023.html.json"},{"name":"20231.html","length":279817,"mtimeUtc":"2026-06-05T16:19:18.5751140Z","cacheFile":"20231.html.json"},{"name":"2024.html","length":514880,"mtimeUtc":"2026-06-05T16:19:23.5530286Z","cacheFile":"2024.html.json"},{"name":"20241.html","length":220391,"mtimeUtc":"2026-06-05T16:19:18.0777686Z","cacheFile":"20241.html.json"},{"name":"2025.html","length":549536,"mtimeUtc":"2026-06-05T16:19:23.0524374Z","cacheFile":"2025.html.json"},{"name":"20251.html","length":208662,"mtimeUtc":"2026-06-05T16:19:17.5797719Z","cacheFile":"20251.html.json"},{"name":"am.html","length":240060,"mtimeUtc":"2026-06-05T16:19:15.0822088Z","cacheFile":"am.html.json"},{"name":"am1.html","length":15331,"mtimeUtc":"2026-06-05T16:19:26.0917857Z","cacheFile":"am1.html.json"},{"name":"am100.html","length":156548,"mtimeUtc":"2026-06-05T16:19:22.0364719Z","cacheFile":"am100.html.json"},{"name":"am2.html","length":15332,"mtimeUtc":"2026-06-05T16:19:20.5542632Z","cacheFile":"am2.html.json"},{"name":"am20.html","length":38106,"mtimeUtc":"2026-06-05T16:19:21.0472244Z","cacheFile":"am20.html.json"},{"name":"am200.html","length":239488,"mtimeUtc":"2026-06-05T16:19:22.5322494Z","cacheFile":"am200.html.json"},{"name":"am50.html","length":82513,"mtimeUtc":"2026-06-05T16:19:21.5535663Z","cacheFile":"am50.html.json"},{"name":"hk.html","length":99078,"mtimeUtc":"2026-06-05T16:19:13.5976677Z","cacheFile":"hk.html.json"},{"name":"hk1.html","length":15125,"mtimeUtc":"2026-06-05T16:19:14.0857962Z","cacheFile":"hk1.html.json"},{"name":"hk100.html","length":97430,"mtimeUtc":"2026-06-05T16:19:16.5779329Z","cacheFile":"hk100.html.json"},{"name":"hk2.html","length":15124,"mtimeUtc":"2026-06-05T16:19:14.5806330Z","cacheFile":"hk2.html.json"},{"name":"hk20.html","length":38204,"mtimeUtc":"2026-06-05T16:19:15.5756613Z","cacheFile":"hk20.html.json"},{"name":"hk200.html","length":97430,"mtimeUtc":"2026-06-05T16:19:17.0753416Z","cacheFile":"hk200.html.json"},{"name":"hk50.html","length":82619,"mtimeUtc":"2026-06-05T16:19:16.0765605Z","cacheFile":"hk50.html.json"}]}